database/DatabaseConnector.py
database/DatabaseDataManager.py
database/DatabaseEntity.py
database/FileDataManager.py
database/__init__.py
database/database.py
database_manager-0.1.0.dist-info/LICENSE
database_manager-0.1.0.dist-info/METADATA
database_manager-0.1.0.dist-info/WHEEL
database_manager-0.1.0.dist-info/top_level.txt
database_manager-0.1.0.dist-info/RECORD
