Metadata-Version: 2.1
Name: database-manager
Version: 0.1.0
Summary: Database Manager for MySQL
Home-page: https://github.com/ShaneBByers/DatabaseManager
Author: Shane Byers
Author-email: shane@shane-byers.com
License: UNKNOWN
Platform: UNKNOWN
Classifier: Programming Language :: Python :: 3
Classifier: License :: OSI Approved :: MIT License
Classifier: Operating System :: OS Independent
Requires-Python: >=3.6
Requires-Dist: mysql-connector
